sdkms_cli/VERSION
sdkms_cli/__init__.py
sdkms_cli/__main__.py
sdkms_cli/pycompatible.py
smartkey_cli-5.4.2891.dist-info/METADATA
smartkey_cli-5.4.2891.dist-info/WHEEL
smartkey_cli-5.4.2891.dist-info/entry_points.txt
smartkey_cli-5.4.2891.dist-info/top_level.txt
smartkey_cli-5.4.2891.dist-info/RECORD
