Metadata-Version: 2.1
Name: smartkey-cli
Version: 5.4.2891
Summary: Equinix Smartkey CLI
Home-page: https://support.smartkey.io
Author: Equinix
Author-email: support@equinix.com
License: Apache 2.0
Keywords: CLI,Equinix Smartkey,Fortanix
Classifier: Development Status :: 5 - Production/Stable
Classifier: Intended Audience :: Developers
Classifier: Intended Audience :: System Administrators
Classifier: License :: OSI Approved :: Apache Software License
Classifier: Programming Language :: Python :: 2
Classifier: Programming Language :: Python :: 3
Classifier: Topic :: Security :: Cryptography
Requires-Dist: argparse ==1.4.0
Requires-Dist: requests ==2.18.4
Requires-Dist: sdkms ==5.4.2891
Requires-Dist: six ==1.11.0
Requires-Dist: urllib3 ==1.21.1
Requires-Dist: enum34 >=1.1.2 ; python_version <= "3.3"
